pysass.py
pysass-0.1.0.dist-info/LICENSE
pysass-0.1.0.dist-info/METADATA
pysass-0.1.0.dist-info/WHEEL
pysass-0.1.0.dist-info/entry_points.txt
pysass-0.1.0.dist-info/top_level.txt
pysass-0.1.0.dist-info/RECORD
